[
  {
    "id": 0,
    "name": "Story Book",
    "title": "lorem10 In this HTML tutorial, you will find more than 200 examples. With our online",
    "price": 0,
    "category": "Free",
    "image": "https://www.zastavki.com/pictures/originals/2014/Creative_Wallpaper_Stack_of_books_on_the_bench_082401_.jpg"
  },
  {
    "id": 1,
    "name": "Music Book",
    "title": "lorem10 In this HTML tutorial, you will find more than 200 examples. With our online",
    "price": 100,
    "category": "song",
    "image": "https://www.zastavki.com/pictures/originals/2014/Creative_Wallpaper_Stack_of_books_on_the_bench_082401_.jpg"
  },
  {
    "id": 2,
    "name": "Drama Book",
    "title": "lorem10 In this HTML tutorial, you will find more than 200 examples. With our online",
    "price": 20,
    "category": "Free",
    "image": "https://www.zastavki.com/pictures/originals/2014/Creative_Wallpaper_Stack_of_books_on_the_bench_082401_.jpg"
  },
  {
    "id": 3,
    "name": "Music Book",
    "title": "lorem10 In this HTML tutorial, you will find more than 200 examples. With our online",
    "price": 30,
    "category": "Free",
    "image": "https://www.zastavki.com/pictures/originals/2014/Creative_Wallpaper_Stack_of_books_on_the_bench_082401_.jpg"
  },
  {
    "id": 4,
    "name": "Story Book",
    "title": "lorem10 In this HTML tutorial, you will find more than 200 examples. With our online",
    "price": 0,
    "category": "Free",
    "image": "https://www.zastavki.com/pictures/originals/2014/Creative_Wallpaper_Stack_of_books_on_the_bench_082401_.jpg"
  },
  {
    "id": 5,
    "name": "food Book",
    "title": "lorem10 In this HTML tutorial, you will find more than 200 examples. With our online",
    "price": 200,
    "category": "Food",
    "image": "https://www.zastavki.com/pictures/originals/2014/Creative_Wallpaper_Stack_of_books_on_the_bench_082401_.jpg"
  },
  {
    "id": 6,
    "name": "Story Book",
    "title": "lorem10 In this HTML tutorial, you will find more than 200 examples. With our online",
    "price": 0,
    "category": "Free",
    "image": "https://www.zastavki.com/pictures/originals/2014/Creative_Wallpaper_Stack_of_books_on_the_bench_082401_.jpg"
  },
  {
    "id": 7,
    "name": "Story Book",
    "title": "lorem10 In this HTML tutorial, you will find more than 200 examples. With our online",
    "price": 0,
    "category": "Free",
    "image": "https://www.zastavki.com/pictures/originals/2014/Creative_Wallpaper_Stack_of_books_on_the_bench_082401_.jpg"
  },
  {
    "id": 8,
    "name": "Sports Book",
    "title": "lorem10 In this HTML tutorial, you will find more than 200 examples. With our online",
    "price": 50,
    "category": "Sports",
    "image": "https://www.zastavki.com/pictures/originals/2014/Creative_Wallpaper_Stack_of_books_on_the_bench_082401_.jpg"
  },
  {
    "id": 9,
    "name": "Comedy Book",
    "title": "lorem10 In this HTML tutorial, you will find more than 200 examples. With our online",
    "price": 20,
    "category": "Entainment",
    "image": "https://www.zastavki.com/pictures/originals/2014/Creative_Wallpaper_Stack_of_books_on_the_bench_082401_.jpg"
  },
  {
    "id": 10,
    "name": "Story Book",
    "title": "lorem10 In this HTML tutorial, you will find more than 200 examples. With our online",
    "price": 0,
    "category": "Free",
    "image": "https://www.zastavki.com/pictures/originals/2014/Creative_Wallpaper_Stack_of_books_on_the_bench_082401_.jpg"
  }
]
